{
	"description": "项目配置文件",
	"packOptions": {
		"ignore": []
	},
	"setting": {
		"urlCheck": false,
		"es6": true,
		"enhance": true,
		"postcss": true,
		"minified": true,
		"newFeature": true,
		"coverView": true,
		"autoAudits": false,
		"checkInvalidKey": true,
		"checkSiteMap": false,
		"uploadWithSourceMap": true,
		"babelSetting": {
			"ignore": [],
			"disablePlugins": [],
			"outputPath": ""
		}
	},
	"compileType": "miniprogram",
	"libVersion": "2.7.7",
	"appid": "wx8edcf72d0f76ad26",
	"projectname": "%E5%8D%95%E8%AF%8D%E5%AE%88%E5%8D%AB",
	"debugOptions": {
		"hidedInDevtools": []
	},
	"isGameTourist": false,
	"simulatorType": "wechat",
	"simulatorPluginLibVersion": {},
	"condition": {
		"search": {
			"current": -1,
			"list": []
		},
		"conversation": {
			"current": -1,
			"list": []
		},
		"plugin": {
			"current": -1,
			"list": []
		},
		"game": {
			"currentL": -1,
			"list": []
		},
		"miniprogram": {
			"current": 31,
			"list": [
				{
					"id": 0,
					"name": "定位",
					"pathName": "pages/pages-list/location/location",
					"query": "",
					"scene": null
				},
				{
					"id": 1,
					"name": "pages/pages-list/poster/poster",
					"pathName": "pages/pages-list/poster/poster",
					"query": "",
					"scene": null
				},
				{
					"id": 2,
					"name": "条形码二维码",
					"pathName": "pages/pages-list/codes/codes",
					"query": "",
					"scene": null
				},
				{
					"id": 3,
					"name": "生成海报",
					"pathName": "pages/pages-list/barcode/barcode",
					"query": "",
					"scene": null
				},
				{
					"id": -1,
					"name": "日历",
					"pathName": "pages/pages-list/calendar/calendar",
					"query": "",
					"scene": null
				},
				{
					"id": -1,
					"name": "地图",
					"pathName": "pages/map/map-world",
					"query": "",
					"scene": null
				},
				{
					"id": -1,
					"name": "地图-亚洲",
					"pathName": "pages/mapdetailed/asia/index",
					"query": "",
					"scene": null
				},
				{
					"id": -1,
					"name": "题目1",
					"pathName": "pages/subject/one/index",
					"query": "",
					"scene": null
				},
				{
					"id": -1,
					"name": "题目2",
					"pathName": "pages/subject/two/index",
					"query": "",
					"scene": null
				},
				{
					"id": -1,
					"name": "题目3",
					"pathName": "pages/subject/three/index",
					"query": "",
					"scene": null
				},
				{
					"id": -1,
					"name": "题目4",
					"pathName": "pages/subject/four/index",
					"query": "",
					"scene": null
				},
				{
					"id": 12,
					"name": "题目5",
					"pathName": "pages/subject/fives/index",
					"query": "",
					"scene": null
				},
				{
					"id": 13,
					"name": "题目6",
					"pathName": "pages/subject/six/index",
					"query": "",
					"scene": null
				},
				{
					"id": -1,
					"name": "题目7",
					"pathName": "pages/subject/seven/index",
					"query": "",
					"scene": null
				},
				{
					"id": -1,
					"name": "题目8",
					"pathName": "pages/subject/eight/index",
					"query": "",
					"scene": null
				},
				{
					"id": -1,
					"name": "题目9",
					"pathName": "pages/subject/nine/index",
					"query": "",
					"scene": null
				},
				{
					"id": -1,
					"name": "题目10",
					"pathName": "pages/subject/ten/index",
					"query": "",
					"scene": null
				},
				{
					"id": -1,
					"name": "题目11",
					"pathName": "pages/subject/eleven/index",
					"query": "",
					"scene": null
				},
				{
					"id": -1,
					"name": "题目12",
					"pathName": "pages/subject/twelve/index",
					"query": "",
					"scene": null
				},
				{
					"id": -1,
					"name": "city",
					"pathName": "pages/city/index",
					"query": "",
					"scene": null
				},
				{
					"id": -1,
					"name": "station",
					"pathName": "pages/station/index",
					"query": "",
					"scene": null
				},
				{
					"id": 22,
					"name": "achievments",
					"pathName": "pages/Achievements/index",
					"query": "",
					"scene": null
				},
				{
					"id": -1,
					"name": "rankinglist",
					"pathName": "pages/rankinglist/rankinglist",
					"query": "",
					"scene": null
				},
				{
					"id": -1,
					"name": "login",
					"pathName": "pages/login/login",
					"query": "",
					"scene": null
				},
				{
					"id": -1,
					"name": "clearance",
					"pathName": "pages/clearance/index",
					"query": "",
					"scene": null
				},
				{
					"id": -1,
					"name": "scores-ranking",
					"pathName": "pages/scores-ranking/scores-ranking",
					"query": "",
					"scene": null
				},
				{
					"id": -1,
					"name": "ranking",
					"pathName": "pages/ranking/index",
					"query": "",
					"scene": null
				},
				{
					"id": -1,
					"name": "synthesize",
					"pathName": "pages/synthesize/index",
					"query": "",
					"scene": null
				},
				{
					"id": -1,
					"name": "欧洲",
					"pathName": "pages/mapdetailed/europe/index",
					"query": "",
					"scene": null
				},
				{
					"id": -1,
					"name": "非洲",
					"pathName": "pages/mapdetailed/africa/index",
					"query": "",
					"scene": null
				},
				{
					"id": -1,
					"name": "北美洲",
					"pathName": "pages/mapdetailed/northamerica/index",
					"query": "",
					"scene": null
				},
				{
					"id": -1,
					"name": "世界地图",
					"pathName": "pages/map/index",
					"query": "",
					"scene": null
				}
			]
		}
	}
}